{
 "meta": {
  "fbref_id": "1961b2aa",
  "player_name": "André Gomes",
  "nation": "POR",
  "age_years": 29.0,
  "squad": "Lille",
  "comps": "Ligue 1",
  "pos_primary": "MF",
  "minutes_2023": 493.0
 },
 "current": {
  "ability": 51.2,
  "score_position": 49.9,
  "score_style": 52.5,
  "groups": {
   "prod": 31.8,
   "progress": 63.0,
   "chance": 37.5,
   "stability": 35.0,
   "defense": 54.1
  }
 },
 "style": {
  "primary": "수비형 파괴자",
  "confidence": 0.37
 },
 "eligibility": {
  "eligible_for_prediction": true,
  "kind": "peak",
  "reason": null
 },
 "prediction": {
  "survival_prob": 0.0739,
  "mu": 51.9,
  "ci80": {
   "lo": 42.4,
   "hi": 61.4
  },
  "ci50": {
   "lo": 46.9,
   "hi": 56.9
  },
  "sigma_model": 2.1,
  "sigma_residual": 7.1
 },
 "neighbors": [
  {
   "fbref_id": "0e50f929",
   "season": 2020,
   "distance": 1.749,
   "survived": 0,
   "fut_ability_v2": null,
   "player_name": "Fran Mérida",
   "squad": "Osasuna"
  },
  {
   "fbref_id": "8c65eb5f",
   "season": 2020,
   "distance": 1.949,
   "survived": 0,
   "fut_ability_v2": null,
   "player_name": "Mato Jajalo",
   "squad": "Udinese"
  },
  {
   "fbref_id": "e8c930bb",
   "season": 2020,
   "distance": 2.042,
   "survived": 1,
   "fut_ability_v2": 55.9,
   "player_name": "Milan Badelj",
   "squad": "Fiorentina"
  },
  {
   "fbref_id": "c53083ad",
   "season": 2020,
   "distance": 2.089,
   "survived": 0,
   "fut_ability_v2": null,
   "player_name": "Bryan Dabo",
   "squad": "SPAL"
  },
  {
   "fbref_id": "542cc80f",
   "season": 2019,
   "distance": 2.095,
   "survived": 1,
   "fut_ability_v2": 52.6,
   "player_name": "Paul Lasne",
   "squad": "Montpellier"
  },
  {
   "fbref_id": "111c3236",
   "season": 2020,
   "distance": 2.112,
   "survived": 0,
   "fut_ability_v2": null,
   "player_name": "Fabian Delph",
   "squad": "Everton"
  },
  {
   "fbref_id": "467bae22",
   "season": 2020,
   "distance": 2.165,
   "survived": 0,
   "fut_ability_v2": null,
   "player_name": "Franco Vázquez",
   "squad": "Sevilla"
  },
  {
   "fbref_id": "756959aa",
   "season": 2018,
   "distance": 2.265,
   "survived": 0,
   "fut_ability_v2": null,
   "player_name": "Blerim Džemaili",
   "squad": "Bologna"
  },
  {
   "fbref_id": "375622c5",
   "season": 2020,
   "distance": 2.283,
   "survived": 1,
   "fut_ability_v2": 50.4,
   "player_name": "Jordan Ferri",
   "squad": "Montpellier"
  },
  {
   "fbref_id": "468fdbad",
   "season": 2019,
   "distance": 2.284,
   "survived": 1,
   "fut_ability_v2": 53.5,
   "player_name": "Jonas Martin",
   "squad": "Strasbourg"
  }
 ],
 "low_confidence": false
}