{
 "meta": {
  "fbref_id": "2077ae86",
  "player_name": "Jonas Wind",
  "nation": "DEN",
  "age_years": 25.0,
  "squad": "Wolfsburg",
  "comps": "Bundesliga",
  "pos_primary": "FW",
  "minutes_season": 1966.0
 },
 "current": {
  "ability": 52.6,
  "score_position": 51.9,
  "score_style": 53.4,
  "groups": {
   "prod": 42.9,
   "progress": 43.3,
   "chance": 58.6,
   "stability": 43.1,
   "defense": 62.3
  }
 },
 "style": {
  "primary": "연결형 공격수",
  "confidence": 0.35
 },
 "eligibility": {
  "eligible_for_prediction": true,
  "kind": "peak",
  "reason": null
 },
 "prediction": {
  "survival_prob": 0.1986,
  "mu": 48.5,
  "ci80": {
   "lo": 39.1,
   "hi": 57.9
  },
  "ci50": {
   "lo": 43.5,
   "hi": 53.5
  },
  "sigma_model": 2.0,
  "sigma_residual": 7.1
 },
 "neighbors": [
  {
   "fbref_id": "2677a1de",
   "season": 2018,
   "distance": 2.837,
   "survived": 1,
   "fut_ability_v2": 52.1,
   "player_name": "Wahbi Khazri",
   "squad": "Rennes"
  },
  {
   "fbref_id": "1f8c7aa9",
   "season": 2018,
   "distance": 2.883,
   "survived": 0,
   "fut_ability_v2": null,
   "player_name": "Ronny Rodelin",
   "squad": "Caen"
  },
  {
   "fbref_id": "d87e2cae",
   "season": 2019,
   "distance": 2.997,
   "survived": 1,
   "fut_ability_v2": 43.7,
   "player_name": "Willian José",
   "squad": "Real Sociedad"
  },
  {
   "fbref_id": "ba115a40",
   "season": 2020,
   "distance": 3.074,
   "survived": 0,
   "fut_ability_v2": null,
   "player_name": "Sébastien Haller",
   "squad": "West Ham"
  },
  {
   "fbref_id": "4f16405e",
   "season": 2019,
   "distance": 3.165,
   "survived": 0,
   "fut_ability_v2": null,
   "player_name": "Niclas Füllkrug",
   "squad": "Hannover 96"
  },
  {
   "fbref_id": "81255c03",
   "season": 2019,
   "distance": 3.191,
   "survived": 1,
   "fut_ability_v2": 47.0,
   "player_name": "João Pedro",
   "squad": "Cagliari"
  },
  {
   "fbref_id": "ab070c55",
   "season": 2018,
   "distance": 3.301,
   "survived": 1,
   "fut_ability_v2": 57.4,
   "player_name": "Christian Benteke",
   "squad": "Crystal Palace"
  },
  {
   "fbref_id": "4f16405e",
   "season": 2018,
   "distance": 3.329,
   "survived": 0,
   "fut_ability_v2": null,
   "player_name": "Niclas Füllkrug",
   "squad": "Hannover 96"
  },
  {
   "fbref_id": "ef5b337e",
   "season": 2019,
   "distance": 3.349,
   "survived": 0,
   "fut_ability_v2": null,
   "player_name": "Fabio Borini",
   "squad": "Milan"
  },
  {
   "fbref_id": "d87e2cae",
   "season": 2018,
   "distance": 3.353,
   "survived": 1,
   "fut_ability_v2": 43.8,
   "player_name": "Willian José",
   "squad": "Real Sociedad"
  }
 ],
 "low_confidence": false,
 "report": {
  "strengths": [
   {
    "key": "AerPct",
    "label": "공중볼 승률",
    "percentile": 96.0
   },
   {
    "key": "AerWon",
    "label": "공중볼 승리",
    "percentile": 95.1
   },
   {
    "key": "F3Pass",
    "label": "최종 3분의1 패스",
    "percentile": 94.4
   },
   {
    "key": "PrgPass",
    "label": "전진 패스",
    "percentile": 92.3
   },
   {
    "key": "TklPct",
    "label": "태클 성공률",
    "percentile": 81.4
   },
   {
    "key": "PrgDistP",
    "label": "전진 패스 거리",
    "percentile": 78.3
   },
   {
    "key": "xAG",
    "label": "도움 기대값(xAG)",
    "percentile": 76.2
   }
  ],
  "weaknesses": [
   {
    "key": "TakeOn",
    "label": "성공 드리블",
    "percentile": 5.6
   },
   {
    "key": "PrgCarry",
    "label": "전진 운반",
    "percentile": 9.8
   },
   {
    "key": "PrgDistC",
    "label": "전진 운반 거리",
    "percentile": 11.7
   },
   {
    "key": "PrgRec",
    "label": "전진 패스 수신",
    "percentile": 13.5
   },
   {
    "key": "SoT",
    "label": "유효슈팅",
    "percentile": 13.8
   }
  ],
  "position_radar": [
   {
    "key": "npxG",
    "label": "비페널티 xG",
    "percentile": 24.7
   },
   {
    "key": "SCA",
    "label": "슈팅 창출(SCA)",
    "percentile": 59.0
   },
   {
    "key": "TakeOn",
    "label": "성공 드리블",
    "percentile": 5.6
   },
   {
    "key": "PrgCarry",
    "label": "전진 운반",
    "percentile": 9.8
   },
   {
    "key": "AttPenT",
    "label": "박스 터치",
    "percentile": 41.0
   },
   {
    "key": "KP",
    "label": "키패스",
    "percentile": 74.1
   }
  ],
  "top3_styles": [
   {
    "style": "연결형 공격수",
    "fit_z": 1.21
   },
   {
    "style": "타겟맨",
    "fit_z": 0.85
   },
   {
    "style": "박스 포처",
    "fit_z": -0.45
   }
  ],
  "style_evidence": {
   "top": [
    {
     "label": "중원 활동 비중",
     "z": 1.72
    },
    {
     "label": "키패스 비중",
     "z": 0.7
    }
   ],
   "bottom": []
  },
  "coaching": [
   "키패스 이미 강점 — 유지 및 응용 훈련 (상위 26퍼센타일)",
   "슈팅 창출(SCA) 강화 여지 — 난이도를 높인 반복 훈련 (현재 59퍼센타일)",
   "전진 패스 수신 개선 필요 — 기초 반복 훈련 권장 (현재 하위 14퍼센타일)"
  ],
  "roadmap": [
   {
    "phase": "0~6주",
    "focus": "전진 패스 수신 기초 교정",
    "kpi": "전진 패스 수신: 14 → 60 퍼센타일"
   },
   {
    "phase": "6~12주",
    "focus": "슈팅 창출(SCA) 실전 적용 반복",
    "kpi": "슈팅 창출(SCA): 59 → 70 퍼센타일"
   },
   {
    "phase": "12주+",
    "focus": "강점 유지 및 상위 리그 수준 경쟁력 전이",
    "kpi": "키패스: 74 → 80 퍼센타일"
   }
  ]
 },
 "qualitative": {
  "discipline": {
   "yellows_per90": 0.09,
   "fouls_per90": 0.69,
   "reds_total_season": 0.0,
   "clean_pctl_cards": 70.6,
   "clean_pctl_fouls": 85.1
  },
  "availability": {
   "minpct_mean": 36.1,
   "n_seasons": 3
  },
  "consistency": {
   "ability_std": 5.5,
   "n_rated_seasons": 2
  }
 },
 "narrative": {
  "current": "Jonas Wind(FW)의 현재 능력 점수는 52.6점이다. 플레이스타일은 '연결형 공격수'로 분류된다. 가장 두드러지는 항목은 수비 그룹이며, 세부 강점은 공중볼 승률, 공중볼 승리, 최종 3분의1 패스 순으로 나타난다. 상대적으로 보완이 필요한 부분은 성공 드리블, 전진 운반이다.",
  "potential": "Jonas Wind의 2~3년 후 전성기 유지 예측 중심값은 48.5점, 80% 구간 상단(잠재력 상한)은 57.9점이다. 빅5 현역 유지확률은 19.9%로 추정된다. 종합하면 현재 대비 추가 성장 경향으로 예측된다 (단, 이 모델의 R²는 0.502로 예측에는 상당한 불확실성이 남아있다)."
 }
}