{
 "meta": {
  "fbref_id": "282f75f3",
  "player_name": "Lewis Dunk",
  "nation": "ENG",
  "age_years": 30.0,
  "squad": "Brighton",
  "comps": "Premier League",
  "pos_primary": "DF",
  "minutes_2023": 1080.0
 },
 "current": {
  "ability": 43.0,
  "score_position": 42.4,
  "score_style": 43.5,
  "groups": {
   "prod": 57.4,
   "progress": 40.5,
   "chance": 19.9,
   "stability": 55.4,
   "defense": 39.0
  }
 },
 "style": {
  "primary": "빌드업 수비수",
  "confidence": 0.59
 },
 "eligibility": {
  "eligible_for_prediction": false,
  "reason": "over_age"
 },
 "prediction": null,
 "neighbors": [],
 "low_confidence": false
}