{
 "meta": {
  "fbref_id": "3312f911",
  "player_name": "Jeffrey Schlupp",
  "nation": "GHA",
  "age_years": 29.0,
  "squad": "Crystal Palace",
  "comps": "Premier League",
  "pos_primary": "MF",
  "minutes_2023": 914.0
 },
 "current": {
  "ability": 37.8,
  "score_position": 32.3,
  "score_style": 43.3,
  "groups": {
   "prod": 37.9,
   "progress": 32.8,
   "chance": 14.9,
   "stability": 24.5,
   "defense": 59.3
  }
 },
 "style": {
  "primary": "수비형 파괴자",
  "confidence": 0.42
 },
 "eligibility": {
  "eligible_for_prediction": true,
  "kind": "peak",
  "reason": null
 },
 "prediction": {
  "survival_prob": 0.3878,
  "mu": 42.5,
  "ci80": {
   "lo": 33.8,
   "hi": 51.2
  },
  "ci50": {
   "lo": 37.9,
   "hi": 47.1
  },
  "sigma_model": 1.867,
  "sigma_residual": 6.562
 },
 "neighbors": [
  {
   "fbref_id": "3c05e082",
   "season": 2018,
   "distance": 1.394,
   "survived": 0,
   "fut_ability_v2": null,
   "player_name": "Koo Ja-cheol",
   "squad": "Augsburg"
  },
  {
   "fbref_id": "90b70194",
   "season": 2019,
   "distance": 1.509,
   "survived": 1,
   "fut_ability_v2": 41.6,
   "player_name": "Përparim Hetemaj",
   "squad": "Chievo"
  },
  {
   "fbref_id": "74e12f1e",
   "season": 2020,
   "distance": 1.8,
   "survived": 1,
   "fut_ability_v2": 35.0,
   "player_name": "Jack Cork",
   "squad": "Burnley"
  },
  {
   "fbref_id": "cedb3e36",
   "season": 2019,
   "distance": 1.837,
   "survived": 1,
   "fut_ability_v2": 35.8,
   "player_name": "Artur Ioniță",
   "squad": "Cagliari"
  },
  {
   "fbref_id": "74e12f1e",
   "season": 2018,
   "distance": 1.938,
   "survived": 1,
   "fut_ability_v2": 39.8,
   "player_name": "Jack Cork",
   "squad": "Burnley"
  },
  {
   "fbref_id": "a64cbd35",
   "season": 2019,
   "distance": 1.972,
   "survived": 0,
   "fut_ability_v2": null,
   "player_name": "Antonino Barillà",
   "squad": "Parma"
  },
  {
   "fbref_id": "8d3c902d",
   "season": 2019,
   "distance": 2.01,
   "survived": 1,
   "fut_ability_v2": 48.4,
   "player_name": "Cheikhou Kouyaté",
   "squad": "Crystal Palace"
  },
  {
   "fbref_id": "8d3c902d",
   "season": 2018,
   "distance": 2.064,
   "survived": 1,
   "fut_ability_v2": 46.8,
   "player_name": "Cheikhou Kouyaté",
   "squad": "West Ham"
  },
  {
   "fbref_id": "036bba5f",
   "season": 2019,
   "distance": 2.104,
   "survived": 1,
   "fut_ability_v2": 55.0,
   "player_name": "Rubén Alcaraz",
   "squad": "Valladolid"
  },
  {
   "fbref_id": "b98570d1",
   "season": 2018,
   "distance": 2.108,
   "survived": 1,
   "fut_ability_v2": 39.8,
   "player_name": "Jake Livermore",
   "squad": "West Brom"
  }
 ],
 "low_confidence": false
}