{
 "meta": {
  "fbref_id": "35d4f151",
  "player_name": "Rubén",
  "nation": "ESP",
  "age_years": 21.0,
  "squad": "Espanyol",
  "comps": "La Liga",
  "pos_primary": "MF",
  "minutes_2023": 244.0
 },
 "current": {
  "ability": 43.9,
  "score_position": 43.3,
  "score_style": 44.4,
  "groups": {
   "prod": 39.5,
   "progress": 50.6,
   "chance": 24.4,
   "stability": 7.6,
   "defense": 84.2
  }
 },
 "style": {
  "primary": "볼 운반형",
  "confidence": 0.26
 },
 "eligibility": {
  "eligible_for_prediction": false,
  "kind": null,
  "reason": "under_minutes"
 },
 "prediction": null,
 "neighbors": [],
 "low_confidence": false,
 "report": {
  "strengths": [
   {
    "key": "AerPct",
    "label": "공중볼 승률",
    "percentile": 100.0
   },
   {
    "key": "TklInt",
    "label": "태클+인터셉트",
    "percentile": 100.0
   },
   {
    "key": "TklPct",
    "label": "태클 성공률",
    "percentile": 100.0
   },
   {
    "key": "PrgRec",
    "label": "전진 패스 수신",
    "percentile": 94.5
   },
   {
    "key": "AerWon",
    "label": "공중볼 승리",
    "percentile": 92.1
   },
   {
    "key": "AttPenT",
    "label": "박스 터치",
    "percentile": 89.7
   },
   {
    "key": "Sh",
    "label": "슈팅 시도",
    "percentile": 88.4
   }
  ],
  "weaknesses": [
   {
    "key": "xAG",
    "label": "도움 기대값(xAG)",
    "percentile": 1.8
   },
   {
    "key": "F3Pass",
    "label": "최종 3분의1 패스",
    "percentile": 5.8
   },
   {
    "key": "PassPct",
    "label": "패스 성공률",
    "percentile": 5.8
   },
   {
    "key": "KP",
    "label": "키패스",
    "percentile": 8.5
   },
   {
    "key": "Err",
    "label": "실책",
    "percentile": 9.4
   }
  ],
  "position_radar": [
   {
    "key": "PrgPass",
    "label": "전진 패스",
    "percentile": 15.5
   },
   {
    "key": "KP",
    "label": "키패스",
    "percentile": 8.5
   },
   {
    "key": "TklInt",
    "label": "태클+인터셉트",
    "percentile": 100.0
   },
   {
    "key": "SCA",
    "label": "슈팅 창출(SCA)",
    "percentile": 55.0
   },
   {
    "key": "PassPct",
    "label": "패스 성공률",
    "percentile": 5.8
   }
  ],
  "top3_styles": [
   {
    "style": "볼 운반형",
    "fit_z": 1.43
   },
   {
    "style": "공격형 MF",
    "fit_z": 1.17
   },
   {
    "style": "수비형 파괴자",
    "fit_z": 0.63
   }
  ],
  "style_evidence": {
   "top": [
    {
     "label": "드리블 시도 비중",
     "z": 1.43
    }
   ],
   "bottom": []
  },
  "coaching": [
   "성공 드리블 이미 강점 — 유지 및 응용 훈련 (상위 13퍼센타일)"
  ],
  "roadmap": [
   {
    "phase": "0~6주",
    "focus": "성공 드리블 기초 교정",
    "kpi": "성공 드리블: 87 → 90 퍼센타일"
   },
   {
    "phase": "12주+",
    "focus": "강점 유지 및 상위 리그 수준 경쟁력 전이",
    "kpi": "성공 드리블: 87 → 90 퍼센타일"
   }
  ]
 },
 "qualitative": {
  "discipline": {
   "yellows_per90": 0.0,
   "fouls_per90": 0.74,
   "reds_total_2023": 0.0,
   "clean_pctl_cards": 81.8,
   "clean_pctl_fouls": 79.0
  },
  "availability": {
   "minpct_mean": 14.5,
   "n_seasons": 2
  },
  "consistency": {
   "ability_std": null,
   "n_rated_seasons": 1
  }
 },
 "narrative": {
  "current": "Rubén(MF)의 현재 능력 점수는 43.9점이다. 플레이스타일은 '볼 운반형'로 분류된다. 가장 두드러지는 항목은 수비 그룹이며, 세부 강점은 공중볼 승률, 태클+인터셉트, 태클 성공률 순으로 나타난다. 상대적으로 보완이 필요한 부분은 도움 기대값(xAG), 최종 3분의1 패스이다.",
  "potential": null
 }
}