{
 "meta": {
  "fbref_id": "3eeb80e0",
  "player_name": "Fredrik Jensen",
  "nation": "FIN",
  "age_years": 25.0,
  "squad": "Augsburg",
  "comps": "Bundesliga",
  "pos_primary": "FW",
  "minutes_2023": 473.0
 },
 "current": {
  "ability": 34.8,
  "score_position": 32.6,
  "score_style": 36.9,
  "groups": {
   "prod": 24.0,
   "progress": 41.5,
   "chance": 38.3,
   "stability": 4.6,
   "defense": 66.0
  }
 },
 "style": {
  "primary": "돌파형 윙어",
  "confidence": 0.94
 },
 "eligibility": {
  "eligible_for_prediction": false,
  "reason": "over_age"
 },
 "prediction": null,
 "neighbors": [],
 "low_confidence": false
}