{
 "meta": {
  "fbref_id": "53cad200",
  "player_name": "César Azpilicueta",
  "nation": "ESP",
  "age_years": 33.0,
  "squad": "Chelsea",
  "comps": "Premier League",
  "pos_primary": "DF",
  "minutes_2023": 537.0
 },
 "current": {
  "ability": 62.2,
  "score_position": 63.2,
  "score_style": 61.2,
  "groups": {
   "prod": 55.8,
   "progress": 74.0,
   "chance": 85.9,
   "stability": 40.8,
   "defense": 67.0
  }
 },
 "style": {
  "primary": "스토퍼",
  "confidence": 0.26
 },
 "eligibility": {
  "eligible_for_prediction": false,
  "reason": "over_age"
 },
 "prediction": null,
 "neighbors": [],
 "low_confidence": false
}