{
 "meta": {
  "fbref_id": "79443529",
  "player_name": "Dušan Vlahović",
  "nation": "SRB",
  "age_years": 22.0,
  "squad": "Juventus",
  "comps": "Serie A",
  "pos_primary": "FW",
  "minutes_2023": 849.0
 },
 "current": {
  "ability": 62.0,
  "score_position": 61.7,
  "score_style": 62.4,
  "groups": {
   "prod": 63.0,
   "progress": 61.5,
   "chance": 54.4,
   "stability": 27.3,
   "defense": 61.3
  }
 },
 "style": {
  "primary": "박스 포처",
  "confidence": 0.1
 },
 "eligibility": {
  "eligible_for_prediction": true,
  "kind": "growth",
  "reason": null
 },
 "prediction": {
  "survival_prob": 0.8635,
  "mu": 50.7,
  "ci80": {
   "lo": 39.3,
   "hi": 62.1
  },
  "ci50": {
   "lo": 44.7,
   "hi": 56.7
  },
  "sigma_model": 3.7,
  "sigma_residual": 8.1
 },
 "neighbors": [
  {
   "fbref_id": "5e080f73",
   "season": 2020,
   "distance": 1.876,
   "survived": 1,
   "fut_ability_v2": 43.1,
   "player_name": "Irvin Cardona",
   "squad": "Brest"
  },
  {
   "fbref_id": "0b90bb97",
   "season": 2020,
   "distance": 2.116,
   "survived": 1,
   "fut_ability_v2": 43.1,
   "player_name": "Santi Mina",
   "squad": "Celta Vigo"
  },
  {
   "fbref_id": "3effaa34",
   "season": 2019,
   "distance": 2.156,
   "survived": 1,
   "fut_ability_v2": 67.6,
   "player_name": "André Silva",
   "squad": "Sevilla"
  },
  {
   "fbref_id": "e5a35ae9",
   "season": 2019,
   "distance": 2.365,
   "survived": 0,
   "fut_ability_v2": null,
   "player_name": "Luca Waldschmidt",
   "squad": "Freiburg"
  },
  {
   "fbref_id": "f8eca1b6",
   "season": 2020,
   "distance": 2.372,
   "survived": 1,
   "fut_ability_v2": 38.5,
   "player_name": "Enes Ünal",
   "squad": "Valladolid"
  },
  {
   "fbref_id": "aa1a8c7e",
   "season": 2018,
   "distance": 2.489,
   "survived": 0,
   "fut_ability_v2": null,
   "player_name": "Isaac Mbenza",
   "squad": "Montpellier"
  },
  {
   "fbref_id": "d705ba44",
   "season": 2018,
   "distance": 2.523,
   "survived": 1,
   "fut_ability_v2": 63.2,
   "player_name": "Andrea Belotti",
   "squad": "Torino"
  },
  {
   "fbref_id": "57e3f0c7",
   "season": 2018,
   "distance": 2.607,
   "survived": 1,
   "fut_ability_v2": 58.3,
   "player_name": "Nicolas Pépé",
   "squad": "Lille"
  },
  {
   "fbref_id": "2054d037",
   "season": 2019,
   "distance": 2.649,
   "survived": 0,
   "fut_ability_v2": null,
   "player_name": "M'Baye Niang",
   "squad": "Rennes"
  },
  {
   "fbref_id": "923f4dda",
   "season": 2020,
   "distance": 2.702,
   "survived": 1,
   "fut_ability_v2": 55.1,
   "player_name": "Sehrou Guirassy",
   "squad": "Amiens"
  }
 ],
 "low_confidence": false
}