{
 "meta": {
  "fbref_id": "93feac6e",
  "player_name": "Patrick Bamford",
  "nation": "ENG",
  "age_years": 29.0,
  "squad": "Leeds United",
  "comps": "Premier League",
  "pos_primary": "FW",
  "minutes_2023": 429.0
 },
 "current": {
  "ability": 50.6,
  "score_position": 48.1,
  "score_style": 53.1,
  "groups": {
   "prod": 67.2,
   "progress": 38.1,
   "chance": 25.9,
   "stability": 36.9,
   "defense": 47.7
  }
 },
 "style": {
  "primary": "박스 포처",
  "confidence": 1.1
 },
 "eligibility": {
  "eligible_for_prediction": false,
  "reason": "over_age"
 },
 "prediction": null,
 "neighbors": [],
 "low_confidence": false
}