{
 "meta": {
  "fbref_id": "d995ed27",
  "player_name": "Giacomo Bonaventura",
  "nation": "ITA",
  "age_years": 33.0,
  "squad": "Fiorentina",
  "comps": "Serie A",
  "pos_primary": "MF",
  "minutes_2023": 757.0
 },
 "current": {
  "ability": 53.3,
  "score_position": 52.7,
  "score_style": 53.9,
  "groups": {
   "prod": 55.3,
   "progress": 50.5,
   "chance": 57.1,
   "stability": 47.7,
   "defense": 55.0
  }
 },
 "style": {
  "primary": "공격형 MF",
  "confidence": 0.77
 },
 "eligibility": {
  "eligible_for_prediction": false,
  "reason": "over_age"
 },
 "prediction": null,
 "neighbors": [],
 "low_confidence": false
}