{
 "meta": {
  "fbref_id": "da052c14",
  "player_name": "Jordan Ayew",
  "nation": "GHA",
  "age_years": 31.0,
  "squad": "Crystal Palace",
  "comps": "Premier League",
  "pos_primary": "MF",
  "minutes_2023": 756.0
 },
 "current": {
  "ability": 46.0,
  "score_position": 46.9,
  "score_style": 45.1,
  "groups": {
   "prod": 53.0,
   "progress": 36.1,
   "chance": 49.5,
   "stability": 27.4,
   "defense": 62.2
  }
 },
 "style": {
  "primary": "볼 운반형",
  "confidence": 0.98
 },
 "eligibility": {
  "eligible_for_prediction": true,
  "kind": "peak",
  "reason": null
 },
 "prediction": {
  "survival_prob": 0.3732,
  "mu": 47.1,
  "ci80": {
   "lo": 37.8,
   "hi": 56.6
  },
  "ci50": {
   "lo": 42.2,
   "hi": 52.1
  },
  "sigma_model": 2.0,
  "sigma_residual": 7.1
 },
 "neighbors": [
  {
   "fbref_id": "79b2399c",
   "season": 2020,
   "distance": 2.208,
   "survived": 1,
   "fut_ability_v2": 50.3,
   "player_name": "Pierrick Capelle",
   "squad": "Angers"
  },
  {
   "fbref_id": "70f8e0bd",
   "season": 2020,
   "distance": 2.307,
   "survived": 1,
   "fut_ability_v2": 45.5,
   "player_name": "Dani Rodríguez",
   "squad": "Mallorca"
  },
  {
   "fbref_id": "90b70194",
   "season": 2018,
   "distance": 2.369,
   "survived": 1,
   "fut_ability_v2": 44.9,
   "player_name": "Përparim Hetemaj",
   "squad": "Chievo"
  },
  {
   "fbref_id": "79b2399c",
   "season": 2018,
   "distance": 2.395,
   "survived": 1,
   "fut_ability_v2": 55.0,
   "player_name": "Pierrick Capelle",
   "squad": "Angers"
  },
  {
   "fbref_id": "76dd1480",
   "season": 2020,
   "distance": 2.495,
   "survived": 0,
   "fut_ability_v2": null,
   "player_name": "Gylfi Sigurðsson",
   "squad": "Everton"
  },
  {
   "fbref_id": "3c05e082",
   "season": 2019,
   "distance": 2.527,
   "survived": 0,
   "fut_ability_v2": null,
   "player_name": "Koo Ja-cheol",
   "squad": "Augsburg"
  },
  {
   "fbref_id": "5aaef9ef",
   "season": 2020,
   "distance": 2.558,
   "survived": 1,
   "fut_ability_v2": 50.8,
   "player_name": "Juraj Kucka",
   "squad": "Parma"
  },
  {
   "fbref_id": "4a57580c",
   "season": 2019,
   "distance": 2.578,
   "survived": 0,
   "fut_ability_v2": null,
   "player_name": "Kévin Monnet-Paquet",
   "squad": "Saint-Étienne"
  },
  {
   "fbref_id": "33b554b7",
   "season": 2020,
   "distance": 2.581,
   "survived": 0,
   "fut_ability_v2": null,
   "player_name": "Danny Latza",
   "squad": "Mainz 05"
  },
  {
   "fbref_id": "cee31595",
   "season": 2019,
   "distance": 2.584,
   "survived": 1,
   "fut_ability_v2": 61.7,
   "player_name": "James McArthur",
   "squad": "Crystal Palace"
  }
 ],
 "low_confidence": false
}