{
 "meta": {
  "fbref_id": "da7b447d",
  "player_name": "Davinson Sánchez",
  "nation": "COL",
  "age_years": 26.0,
  "squad": "Tottenham",
  "comps": "Premier League",
  "pos_primary": "DF",
  "minutes_2023": 497.0
 },
 "current": {
  "ability": 56.0,
  "score_position": 53.2,
  "score_style": 58.7,
  "groups": {
   "prod": 63.1,
   "progress": 37.2,
   "chance": 34.2,
   "stability": 51.5,
   "defense": 65.8
  }
 },
 "style": {
  "primary": "스토퍼",
  "confidence": 1.67
 },
 "eligibility": {
  "eligible_for_prediction": false,
  "reason": "over_age"
 },
 "prediction": null,
 "neighbors": [],
 "low_confidence": false
}