{
 "meta": {
  "fbref_id": "db092d3b",
  "player_name": "Ismaël Bennacer",
  "nation": "ALG",
  "age_years": 24.0,
  "squad": "Milan",
  "comps": "Serie A",
  "pos_primary": "MF",
  "minutes_2023": 845.0
 },
 "current": {
  "ability": 58.9,
  "score_position": 57.7,
  "score_style": 60.1,
  "groups": {
   "prod": 35.9,
   "progress": 60.8,
   "chance": 73.6,
   "stability": 46.2,
   "defense": 67.6
  }
 },
 "style": {
  "primary": "딥 플레이메이커",
  "confidence": 0.24
 },
 "eligibility": {
  "eligible_for_prediction": false,
  "reason": "over_age;under_minutes"
 },
 "prediction": null,
 "neighbors": [],
 "low_confidence": false
}