{
 "meta": {
  "fbref_id": "de39485a",
  "player_name": "Yannick Carrasco",
  "nation": "BEL",
  "age_years": 29.0,
  "squad": "Atlético Madrid",
  "comps": "La Liga",
  "pos_primary": "DF",
  "minutes_2023": 616.0
 },
 "current": {
  "ability": 50.9,
  "score_position": 42.5,
  "score_style": 59.2,
  "groups": {
   "prod": 89.2,
   "progress": 59.9,
   "chance": 78.2,
   "stability": 34.8,
   "defense": 16.2
  }
 },
 "style": {
  "primary": "공격형 풀백",
  "confidence": 2.76
 },
 "eligibility": {
  "eligible_for_prediction": true,
  "kind": "peak",
  "reason": null
 },
 "prediction": {
  "survival_prob": 0.4436,
  "mu": 52.4,
  "ci80": {
   "lo": 42.7,
   "hi": 62.0
  },
  "ci50": {
   "lo": 47.2,
   "hi": 57.5
  },
  "sigma_model": 2.7,
  "sigma_residual": 7.1
 },
 "neighbors": [
  {
   "fbref_id": "852351df",
   "season": 2020,
   "distance": 3.932,
   "survived": 0,
   "fut_ability_v2": null,
   "player_name": "Bruno Peres",
   "squad": "Roma"
  },
  {
   "fbref_id": "d4ef9ac5",
   "season": 2019,
   "distance": 3.995,
   "survived": 0,
   "fut_ability_v2": null,
   "player_name": "Toño",
   "squad": "Levante"
  },
  {
   "fbref_id": "bbafc0c4",
   "season": 2019,
   "distance": 4.06,
   "survived": 1,
   "fut_ability_v2": 57.0,
   "player_name": "Cristian Ansaldi",
   "squad": "Torino"
  },
  {
   "fbref_id": "060606ec",
   "season": 2019,
   "distance": 4.097,
   "survived": 0,
   "fut_ability_v2": null,
   "player_name": "Marco D'Alessandro",
   "squad": "Udinese"
  },
  {
   "fbref_id": "5128bde4",
   "season": 2019,
   "distance": 4.108,
   "survived": 1,
   "fut_ability_v2": 56.3,
   "player_name": "Darko Lazović",
   "squad": "Genoa"
  },
  {
   "fbref_id": "bbafc0c4",
   "season": 2018,
   "distance": 4.136,
   "survived": 1,
   "fut_ability_v2": 55.0,
   "player_name": "Cristian Ansaldi",
   "squad": "Torino"
  },
  {
   "fbref_id": "140afefb",
   "season": 2018,
   "distance": 4.174,
   "survived": 0,
   "fut_ability_v2": null,
   "player_name": "Marcel Risse",
   "squad": "Köln"
  },
  {
   "fbref_id": "44eb9093",
   "season": 2019,
   "distance": 4.206,
   "survived": 1,
   "fut_ability_v2": 55.2,
   "player_name": "Danilo D'Ambrosio",
   "squad": "Inter"
  },
  {
   "fbref_id": "9f323c71",
   "season": 2018,
   "distance": 4.355,
   "survived": 1,
   "fut_ability_v2": 50.2,
   "player_name": "Óscar de Marcos",
   "squad": "Athletic Club"
  },
  {
   "fbref_id": "5128bde4",
   "season": 2020,
   "distance": 4.405,
   "survived": 1,
   "fut_ability_v2": 58.5,
   "player_name": "Darko Lazović",
   "squad": "Hellas Verona"
  }
 ],
 "low_confidence": true
}