{
 "meta": {
  "fbref_id": "e58cbfd5",
  "player_name": "Nicolò Rovella",
  "nation": "ITA",
  "age_years": 20.0,
  "squad": "Monza / Juventus",
  "comps": "Serie A",
  "pos_primary": "MF",
  "minutes_2023": 616.0
 },
 "current": {
  "ability": 43.3,
  "score_position": 42.9,
  "score_style": 43.7,
  "groups": {
   "prod": 35.2,
   "progress": 44.9,
   "chance": 36.9,
   "stability": 49.2,
   "defense": 46.2
  }
 },
 "style": {
  "primary": "딥 플레이메이커",
  "confidence": 0.01
 },
 "eligibility": {
  "eligible_for_prediction": false,
  "reason": "under_minutes"
 },
 "prediction": null,
 "neighbors": [],
 "low_confidence": false
}