{
 "meta": {
  "fbref_id": "eeba07f8",
  "player_name": "Luis Javier Suárez",
  "nation": "COL",
  "age_years": 24.0,
  "squad": "Marseille",
  "comps": "Ligue 1",
  "pos_primary": "FW",
  "minutes_2023": 293.0
 },
 "current": {
  "ability": 77.0,
  "score_position": 75.8,
  "score_style": 78.3,
  "groups": {
   "prod": 87.2,
   "progress": 75.5,
   "chance": 65.8,
   "stability": 21.3,
   "defense": 50.5
  }
 },
 "style": {
  "primary": "박스 포처",
  "confidence": 0.38
 },
 "eligibility": {
  "eligible_for_prediction": false,
  "kind": null,
  "reason": "under_minutes"
 },
 "prediction": null,
 "neighbors": [],
 "low_confidence": false,
 "report": {
  "strengths": [
   {
    "key": "Sh",
    "label": "슈팅 시도",
    "percentile": 100.0
   },
   {
    "key": "npxG",
    "label": "비페널티 xG",
    "percentile": 98.6
   },
   {
    "key": "SoT",
    "label": "유효슈팅",
    "percentile": 98.6
   },
   {
    "key": "Clr",
    "label": "클리어링",
    "percentile": 98.6
   },
   {
    "key": "np_G",
    "label": "무페널티 득점",
    "percentile": 97.2
   },
   {
    "key": "PrgPass",
    "label": "전진 패스",
    "percentile": 96.5
   },
   {
    "key": "TklInt",
    "label": "태클+인터셉트",
    "percentile": 93.6
   }
  ],
  "weaknesses": [
   {
    "key": "PrgRec",
    "label": "전진 패스 수신",
    "percentile": 37.6
   },
   {
    "key": "KP",
    "label": "키패스",
    "percentile": 41.1
   },
   {
    "key": "xAG",
    "label": "도움 기대값(xAG)",
    "percentile": 48.2
   },
   {
    "key": "SCA",
    "label": "슈팅 창출(SCA)",
    "percentile": 53.9
   },
   {
    "key": "TakeOn",
    "label": "성공 드리블",
    "percentile": 59.6
   }
  ],
  "position_radar": [
   {
    "key": "npxG",
    "label": "비페널티 xG",
    "percentile": 98.6
   },
   {
    "key": "SCA",
    "label": "슈팅 창출(SCA)",
    "percentile": 53.9
   },
   {
    "key": "TakeOn",
    "label": "성공 드리블",
    "percentile": 59.6
   },
   {
    "key": "AttPenT",
    "label": "박스 터치",
    "percentile": 83.7
   },
   {
    "key": "KP",
    "label": "키패스",
    "percentile": 41.1
   }
  ],
  "top3_styles": [
   {
    "style": "박스 포처",
    "fit_z": 1.37
   },
   {
    "style": "타겟맨",
    "fit_z": 1.0
   },
   {
    "style": "연결형 공격수",
    "fit_z": -0.11
   }
  ],
  "style_evidence": {
   "top": [
    {
     "label": "슈팅 비중",
     "z": 2.23
    },
    {
     "label": "박스 터치 비중",
     "z": 0.52
    }
   ],
   "bottom": []
  },
  "coaching": [
   "비페널티 xG 이미 강점 — 유지 및 응용 훈련 (상위 1퍼센타일)",
   "유효슈팅 이미 강점 — 유지 및 응용 훈련 (상위 1퍼센타일)",
   "박스 터치 이미 강점 — 유지 및 응용 훈련 (상위 16퍼센타일)"
  ],
  "roadmap": [
   {
    "phase": "0~6주",
    "focus": "박스 터치 기초 교정",
    "kpi": "박스 터치: 84 → 90 퍼센타일"
   },
   {
    "phase": "6~12주",
    "focus": "비페널티 xG 실전 적용 반복",
    "kpi": "비페널티 xG: 이미 상위 1퍼센타일 — 유지"
   },
   {
    "phase": "12주+",
    "focus": "강점 유지 및 상위 리그 수준 경쟁력 전이",
    "kpi": "유효슈팅: 이미 상위 1퍼센타일 — 유지"
   }
  ]
 },
 "qualitative": {
  "discipline": {
   "yellows_per90": 0.31,
   "fouls_per90": 1.84,
   "reds_total_2023": 0.0,
   "clean_pctl_cards": 17.0,
   "clean_pctl_fouls": 8.5
  },
  "availability": {
   "minpct_mean": 52.4,
   "n_seasons": 3
  },
  "consistency": {
   "ability_std": 16.4,
   "n_rated_seasons": 3
  }
 },
 "narrative": {
  "current": "Luis Javier Suárez(FW)의 현재 능력 점수는 77.0점이다. 플레이스타일은 '박스 포처'로 분류된다. 가장 두드러지는 항목은 생산 그룹이며, 세부 강점은 슈팅 시도, 비페널티 xG, 유효슈팅 순으로 나타난다. 상대적으로 보완이 필요한 부분은 전진 패스 수신, 키패스이다.",
  "potential": null
 }
}