{
 "meta": {
  "fbref_id": "f26834c7",
  "player_name": "Karim Onisiwo",
  "nation": "AUT",
  "age_years": 30.0,
  "squad": "Mainz 05",
  "comps": "Bundesliga",
  "pos_primary": "FW",
  "minutes_2023": 1040.0
 },
 "current": {
  "ability": 51.3,
  "score_position": 48.2,
  "score_style": 54.5,
  "groups": {
   "prod": 41.9,
   "progress": 65.0,
   "chance": 52.5,
   "stability": 5.3,
   "defense": 38.9
  }
 },
 "style": {
  "primary": "돌파형 윙어",
  "confidence": 0.57
 },
 "eligibility": {
  "eligible_for_prediction": true,
  "kind": "peak",
  "reason": null
 },
 "prediction": {
  "survival_prob": 0.4392,
  "mu": 63.3,
  "ci80": {
   "lo": 52.5,
   "hi": 74.0
  },
  "ci50": {
   "lo": 57.6,
   "hi": 68.9
  },
  "sigma_model": 4.5,
  "sigma_residual": 7.1
 },
 "neighbors": [
  {
   "fbref_id": "4a478107",
   "season": 2020,
   "distance": 2.318,
   "survived": 1,
   "fut_ability_v2": 71.3,
   "player_name": "José Luis Morales",
   "squad": "Levante"
  },
  {
   "fbref_id": "4a478107",
   "season": 2019,
   "distance": 2.424,
   "survived": 1,
   "fut_ability_v2": 63.4,
   "player_name": "José Luis Morales",
   "squad": "Levante"
  },
  {
   "fbref_id": "02319ad7",
   "season": 2020,
   "distance": 2.725,
   "survived": 0,
   "fut_ability_v2": null,
   "player_name": "Jaime Mata",
   "squad": "Getafe"
  },
  {
   "fbref_id": "2bcc6d52",
   "season": 2018,
   "distance": 2.878,
   "survived": 1,
   "fut_ability_v2": 38.6,
   "player_name": "Guido Burgstaller",
   "squad": "Schalke 04"
  },
  {
   "fbref_id": "b318a643",
   "season": 2019,
   "distance": 2.92,
   "survived": 0,
   "fut_ability_v2": null,
   "player_name": "Salomón Rondón",
   "squad": "Newcastle Utd"
  },
  {
   "fbref_id": "086d7db3",
   "season": 2018,
   "distance": 3.139,
   "survived": 0,
   "fut_ability_v2": null,
   "player_name": "Ivan Santini",
   "squad": "Caen"
  },
  {
   "fbref_id": "b561db50",
   "season": 2020,
   "distance": 3.15,
   "survived": 1,
   "fut_ability_v2": 47.5,
   "player_name": "Raúl Jiménez",
   "squad": "Wolves"
  },
  {
   "fbref_id": "601ef102",
   "season": 2020,
   "distance": 3.184,
   "survived": 0,
   "fut_ability_v2": null,
   "player_name": "Stefano Okaka",
   "squad": "Udinese"
  },
  {
   "fbref_id": "4c7940d6",
   "season": 2018,
   "distance": 3.256,
   "survived": 0,
   "fut_ability_v2": null,
   "player_name": "Massimo Coda",
   "squad": "Benevento"
  },
  {
   "fbref_id": "d520120b",
   "season": 2020,
   "distance": 3.261,
   "survived": 0,
   "fut_ability_v2": null,
   "player_name": "Júlio Tavares",
   "squad": "Dijon"
  }
 ],
 "low_confidence": false
}