{
 "meta": {
  "fbref_id": "f8eca1b6",
  "player_name": "Enes Ünal",
  "nation": "TUR",
  "age_years": 25.0,
  "squad": "Getafe",
  "comps": "La Liga",
  "pos_primary": "FW",
  "minutes_2023": 1032.0
 },
 "current": {
  "ability": 39.6,
  "score_position": 37.4,
  "score_style": 41.6,
  "groups": {
   "prod": 37.8,
   "progress": 27.5,
   "chance": 35.5,
   "stability": 14.2,
   "defense": 55.5
  }
 },
 "style": {
  "primary": "타겟맨",
  "confidence": 0.54
 },
 "eligibility": {
  "eligible_for_prediction": true,
  "kind": "peak",
  "reason": null
 },
 "prediction": {
  "survival_prob": 0.699,
  "mu": 42.4,
  "ci80": {
   "lo": 32.6,
   "hi": 52.2
  },
  "ci50": {
   "lo": 37.2,
   "hi": 47.6
  },
  "sigma_model": 2.9,
  "sigma_residual": 7.1
 },
 "neighbors": [
  {
   "fbref_id": "09538fdb",
   "season": 2019,
   "distance": 2.206,
   "survived": 1,
   "fut_ability_v2": 49.6,
   "player_name": "Kevin Lasagna",
   "squad": "Udinese"
  },
  {
   "fbref_id": "6c1f7328",
   "season": 2018,
   "distance": 2.227,
   "survived": 0,
   "fut_ability_v2": null,
   "player_name": "Roberto Inglese",
   "squad": "Chievo"
  },
  {
   "fbref_id": "6a99e0b1",
   "season": 2020,
   "distance": 2.337,
   "survived": 1,
   "fut_ability_v2": 54.7,
   "player_name": "Iñaki Williams",
   "squad": "Athletic Club"
  },
  {
   "fbref_id": "4e9a0555",
   "season": 2019,
   "distance": 2.387,
   "survived": 1,
   "fut_ability_v2": 36.7,
   "player_name": "Chris Wood",
   "squad": "Burnley"
  },
  {
   "fbref_id": "6922f806",
   "season": 2019,
   "distance": 2.419,
   "survived": 1,
   "fut_ability_v2": 47.8,
   "player_name": "Jonathan Calleri",
   "squad": "Alavés"
  },
  {
   "fbref_id": "462475ed",
   "season": 2020,
   "distance": 2.421,
   "survived": 1,
   "fut_ability_v2": 57.1,
   "player_name": "Ludovic Ajorque",
   "squad": "Strasbourg"
  },
  {
   "fbref_id": "2054d037",
   "season": 2020,
   "distance": 2.491,
   "survived": 0,
   "fut_ability_v2": null,
   "player_name": "M'Baye Niang",
   "squad": "Rennes"
  },
  {
   "fbref_id": "6605d143",
   "season": 2020,
   "distance": 2.506,
   "survived": 1,
   "fut_ability_v2": 51.2,
   "player_name": "Habib Diallo",
   "squad": "Metz"
  },
  {
   "fbref_id": "2691c772",
   "season": 2018,
   "distance": 2.518,
   "survived": 1,
   "fut_ability_v2": 37.1,
   "player_name": "Ashley Barnes",
   "squad": "Burnley"
  },
  {
   "fbref_id": "35f6db55",
   "season": 2018,
   "distance": 2.523,
   "survived": 0,
   "fut_ability_v2": null,
   "player_name": "Léo Baptistão",
   "squad": "Espanyol"
  }
 ],
 "low_confidence": false,
 "report": {
  "strengths": [
   {
    "key": "AerWon",
    "label": "공중볼 승리",
    "percentile": 95.0
   },
   {
    "key": "Clr",
    "label": "클리어링",
    "percentile": 93.6
   },
   {
    "key": "AerPct",
    "label": "공중볼 승률",
    "percentile": 73.8
   },
   {
    "key": "Ast",
    "label": "어시스트",
    "percentile": 64.5
   },
   {
    "key": "GCA",
    "label": "골 창출(GCA)",
    "percentile": 58.9
   },
   {
    "key": "F3Pass",
    "label": "최종 3분의1 패스",
    "percentile": 53.2
   },
   {
    "key": "Recov",
    "label": "볼 리커버리",
    "percentile": 51.8
   }
  ],
  "weaknesses": [
   {
    "key": "AttPenT",
    "label": "박스 터치",
    "percentile": 5.0
   },
   {
    "key": "PrgRec",
    "label": "전진 패스 수신",
    "percentile": 9.9
   },
   {
    "key": "npxG",
    "label": "비페널티 xG",
    "percentile": 18.4
   },
   {
    "key": "TakeOn",
    "label": "성공 드리블",
    "percentile": 24.8
   },
   {
    "key": "KP",
    "label": "키패스",
    "percentile": 25.5
   }
  ],
  "position_radar": [
   {
    "key": "npxG",
    "label": "비페널티 xG",
    "percentile": 18.4
   },
   {
    "key": "SCA",
    "label": "슈팅 창출(SCA)",
    "percentile": 29.1
   },
   {
    "key": "TakeOn",
    "label": "성공 드리블",
    "percentile": 24.8
   },
   {
    "key": "AttPenT",
    "label": "박스 터치",
    "percentile": 5.0
   },
   {
    "key": "KP",
    "label": "키패스",
    "percentile": 25.5
   }
  ],
  "top3_styles": [
   {
    "style": "타겟맨",
    "fit_z": 0.61
   },
   {
    "style": "연결형 공격수",
    "fit_z": 0.07
   },
   {
    "style": "박스 포처",
    "fit_z": -0.55
   }
  ],
  "style_evidence": {
   "top": [
    {
     "label": "공중볼 경합량",
     "z": 2.17
    },
    {
     "label": "박스 터치 비중",
     "z": -0.96
    }
   ],
   "bottom": []
  },
  "coaching": [
   "공중볼 승리 이미 강점 — 유지 및 응용 훈련 (상위 5퍼센타일)",
   "무페널티 득점 강화 여지 — 난이도를 높인 반복 훈련 (현재 52퍼센타일)",
   "박스 터치 개선 필요 — 기초 반복 훈련 권장 (현재 하위 5퍼센타일)"
  ],
  "roadmap": [
   {
    "phase": "0~6주",
    "focus": "박스 터치 기초 교정",
    "kpi": "박스 터치: 5 → 60 퍼센타일"
   },
   {
    "phase": "6~12주",
    "focus": "무페널티 득점 실전 적용 반복",
    "kpi": "무페널티 득점: 52 → 70 퍼센타일"
   },
   {
    "phase": "12주+",
    "focus": "강점 유지 및 상위 리그 수준 경쟁력 전이",
    "kpi": "공중볼 승리: 이미 상위 5퍼센타일 — 유지"
   }
  ]
 },
 "qualitative": {
  "discipline": {
   "yellows_per90": 0.17,
   "fouls_per90": 1.66,
   "reds_total_2023": 0.0,
   "clean_pctl_cards": 41.1,
   "clean_pctl_fouls": 18.4
  },
  "availability": {
   "minpct_mean": 62.4,
   "n_seasons": 6
  },
  "consistency": {
   "ability_std": 3.7,
   "n_rated_seasons": 6
  }
 },
 "narrative": {
  "current": "Enes Ünal(FW)의 현재 능력 점수는 39.6점이다. 플레이스타일은 '타겟맨'로 분류된다. 그룹별 점수는 특별히 두드러지는 항목 없이 대체로 평이하며, 세부 강점은 공중볼 승리, 클리어링, 공중볼 승률 순으로 나타난다. 상대적으로 보완이 필요한 부분은 박스 터치, 전진 패스 수신이다.",
  "potential": "Enes Ünal의 2~3년 후 전성기 유지 예측 중심값은 42.4점, 80% 구간 상단(잠재력 상한)은 52.2점이다. 빅5 현역 유지확률은 69.9%로 추정된다. 종합하면 현재 대비 추가 성장 경향으로 예측된다 (단, 이 모델의 R²는 0.502로 예측에는 상당한 불확실성이 남아있다)."
 }
}