{
 "meta": {
  "fbref_id": "f9758dae",
  "player_name": "Emmanuel Gyasi",
  "nation": "GHA",
  "age_years": 28.0,
  "squad": "Spezia",
  "comps": "Serie A",
  "pos_primary": "FW",
  "minutes_2023": 975.0
 },
 "current": {
  "ability": 20.6,
  "score_position": 20.5,
  "score_style": 20.8,
  "groups": {
   "prod": 12.1,
   "progress": 12.1,
   "chance": 15.8,
   "stability": 48.2,
   "defense": 53.0
  }
 },
 "style": {
  "primary": "연결형 공격수",
  "confidence": 0.04
 },
 "eligibility": {
  "eligible_for_prediction": false,
  "reason": "over_age"
 },
 "prediction": null,
 "neighbors": [],
 "low_confidence": false
}